oceanval/__init__.py
oceanval/chunkers.py
oceanval/fixers.py
oceanval/fvcom.py
oceanval/gridded.py
oceanval/matchall.py
oceanval/parsers.py
oceanval/session.py
oceanval/summarize.py
oceanval/tidiers.py
oceanval/utils.py
oceanval/data/001_methods.ipynb
oceanval/data/TM_WORLD_BORDERS-0.3.dbf
oceanval/data/TM_WORLD_BORDERS-0.3.prj
oceanval/data/TM_WORLD_BORDERS-0.3.shp
oceanval/data/TM_WORLD_BORDERS-0.3.shx
oceanval/data/_config.yml
oceanval/data/_toc.yml
oceanval/data/chunk_bias.py
oceanval/data/chunk_clim.py
oceanval/data/chunk_empty.py
oceanval/data/chunk_end.py
oceanval/data/chunk_globals.py
oceanval/data/chunk_point.py
oceanval/data/chunk_results.py
oceanval/data/chunk_seasonal.py
oceanval/data/chunk_start.py
oceanval/data/comparison_bias.ipynb
oceanval/data/comparison_point.ipynb
oceanval/data/comparison_regional.ipynb
oceanval/data/comparison_seasonal.ipynb
oceanval/data/comparison_spatial.ipynb
oceanval/data/global_subdomains.nc
oceanval/data/gridded_template.ipynb
oceanval/data/intro.md
oceanval/data/intro_compare_simulations.md
oceanval/data/intro_summarize.md
oceanval/data/nwes_subdomains.nc
oceanval/data/pml_logo.jpg
oceanval/data/point_template.ipynb
oceanval/data/requirements.txt
oceanval/data/summary.ipynb
oceanval/data/variable_summary_template.ipynb
oceanval/data/.trackers/nctoolkit_rwi_eseqyqyonctoolkit
oceanval-0.1.9.dist-info/licenses/LICENSE
oceanval-0.1.9.dist-info/METADATA
oceanval-0.1.9.dist-info/WHEEL
oceanval-0.1.9.dist-info/top_level.txt
oceanval-0.1.9.dist-info/RECORD
