Metadata-Version: 2.4
Name: oceanval
Version: 0.1.9
Summary: A Python package for ocean model validation and analysis
Home-page: https://github.com/pmlmodelling/oceanVal
Author: Robert Wilson
Author-email: rwi@pml.ac.uk
Maintainer: Robert Wilson
Project-URL: Bug Tracker, https://github.com/pmlmodelling/oceanVal/issues
Project-URL: Source Code, https://github.com/pmlmodelling/oceanVal
Classifier: License :: OSI Approved :: GNU General Public License v3 (GPLv3)
Classifier: Operating System :: POSIX :: Linux
Classifier: Operating System :: MacOS
Classifier: Programming Language :: Python :: 3.6
Classifier: Programming Language :: Python :: 3.7
Classifier: Programming Language :: Python :: 3.8
Classifier: Programming Language :: Python :: 3.9
Requires-Python: >=3.6.1
License-File: LICENSE
Requires-Dist: xarray
Requires-Dist: netCDF4
Requires-Dist: hvplot
Requires-Dist: panel
Requires-Dist: pandas
Requires-Dist: ncplot
Requires-Dist: dill
Requires-Dist: python-dateutil
Requires-Dist: matplotlib
Requires-Dist: jupytext
Requires-Dist: nctoolkit>=1.1.1
Requires-Dist: geopandas
Requires-Dist: holoviews
Requires-Dist: plotnine
Requires-Dist: jupyter-book==1.0.4
Requires-Dist: fiona
Requires-Dist: multiprocess
Dynamic: author
Dynamic: author-email
Dynamic: classifier
Dynamic: description
Dynamic: home-page
Dynamic: license-file
Dynamic: maintainer
Dynamic: project-url
Dynamic: requires-dist
Dynamic: requires-python
Dynamic: summary
